{
  "pais": "Argentina",
  "categoria": "Vivienda, urbanismo y desarrollo territorial",
  "subcategoria": "Urbanismo y uso del suelo",
  "analisis": {
    "2026-02": "**1. Situación anterior**\n\nEn los últimos diez años, Argentina ha vivido una profundización de los desafíos en torno a la vivienda y la forma en que nuestras ciudades crecen. La historia de ese período es, en gran medida, la de una urbanización acelerada y a menudo descontrolada. El crecimiento demográfico, sumado a los movimientos internos de población hacia los grandes centros urbanos, ejerció una presión inmensa sobre la tierra disponible. Esto llevó a un fenómeno recurrente: la expansión desmedida de las ciudades, donde el cemento avanzaba rápidamente sobre áreas rurales o periurbanas sin una planificación clara que acompañara ese ritmo.\n\nEsta expansión tuvo consecuencias directas. Vimos cómo los precios del suelo se disparaban, convirtiéndolo en un bien cada vez más inaccesible para una parte significativa de la población. La respuesta a esta inaccesibilidad se manifestó en el crecimiento de asentamientos informales y tomas de tierras, un reflejo visible de la falta de soluciones habitacionales y de acceso formal a la tierra. A la par, los esfuerzos gubernamentales, tanto a nivel nacional como provincial, se centraron en programas de construcción de viviendas y, en menor medida, en la regularización dominial de barrios existentes. Sin embargo, estas iniciativas, aunque importantes, a menudo resultaron insuficientes para contener la magnitud del problema y no lograron alterar la tendencia subyacente de un desarrollo urbano reactivo más que planificado. La discusión sobre el uso del suelo, entre la producción agrícola, la preservación ambiental y la necesidad de vivienda, se intensificó, marcando un período de crecientes tensiones territoriales.\n\n**2. Situación actual**\n\nNos encontramos en febrero de 2026, y la situación en materia de urbanismo y uso del suelo en Argentina sigue siendo un tablero complejo, donde coexisten esfuerzos por mejorar la planificación con desafíos estructurales de larga data.\n\n**La Presión del Crecimiento Urbano Desorganizado y la Búsqueda de un Límite**\n\nActualmente, muchas de nuestras ciudades experimentan una fuerte presión sobre sus límites, lo que se traduce en un crecimiento desordenado conocido como \"expansión urbana\". Para contrarrestarlo, varias municipalidades están en proceso de actualizar sus Códigos de Ordenamiento Urbano (COU) o Planes de Desarrollo Territorial. Estos instrumentos buscan definir dónde y cómo se puede construir, establecer zonas residenciales, industriales, o de esparcimiento. Por ejemplo, en el Gran Buenos Aires y en áreas metropolitanas de Córdoba o Rosario, se observa un intento de coordinar estos códigos entre municipios vecinos, aunque con resultados variados. La idea es evitar que un municipio permita construcciones que generen problemas de infraestructura o ambientales en el municipio de al lado.\n\nEstas acciones son impulsadas principalmente por los gobiernos locales, que son los responsables directos de aprobar los permisos de construcción, pero cuentan con el apoyo técnico y, a veces, financiero de organismos provinciales y, en menor medida, de programas federales que buscan una visión más integral. Sin embargo, las consecuencias de esta expansión descontrolada se siguen manifestando en largos viajes diarios para los habitantes de las periferias, una sobrecarga en los servicios públicos como el transporte y la recolección de residuos, y la pérdida irreversible de suelos productivos agrícolas y ecosistemas naturales, como humedales. El gran problema es que las actualizaciones de los COU suelen ser lentas, muy influenciadas por los intereses económicos de los desarrolladores privados y, a menudo, llegan tarde para contener un crecimiento que ya está en marcha. La falta de una visión clara y compartida a nivel regional, sumada a las diferencias políticas entre jurisdicciones, dificulta la implementación de una planificación coherente y efectiva, generando tensiones constantes entre la necesidad de vivienda, la preservación ambiental y los intereses inmobiliarios.\n\n**La Persistencia de la Informalidad y la Lucha por el Acceso al Suelo**\n\nEl desafío más palpable sigue siendo la gran cantidad de asentamientos informales y la dificultad para que muchas familias accedan a un lote con servicios básicos y título de propiedad. En respuesta, se mantienen en marcha programas de integración sociourbana en asentamientos ya consolidados, muchos de ellos financiados con préstamos de organismos internacionales o con fondos específicos de los gobiernos federal y provinciales. Estos programas buscan llevar infraestructura básica –agua, cloacas, luz, calles– y, en lo posible, regularizar la tenencia de la tierra, entregando títulos de propiedad a sus habitantes.\n\nLa ejecución de estas acciones recae principalmente en secretarías o direcciones de vivienda y desarrollo urbano, tanto a nivel federal como provincial, en colaboración estrecha con las municipalidades y, muy importante, con organizaciones sociales y los propios vecinos. Los resultados son mixtos: mientras que en algunos barrios se ha logrado una transformación significativa, mejorando la calidad de vida de miles de familias y reduciendo la vulnerabilidad, el proceso de titulación suele ser extremadamente lento y complejo debido a la maraña legal y burocrática. Esto significa que muchas familias viven con mejoras en su entorno, pero sin la seguridad jurídica de ser dueños de su hogar. Lo que funciona bien es la participación comunitaria, que asegura que las obras respondan a las necesidades reales. El gran problema es que la velocidad de creación de nuevos asentamientos informales, impulsada por el déficit habitacional y la especulación del suelo, supera ampliamente la capacidad de estos programas para integrarlos. La tensión aquí es clara: la urgencia de una necesidad básica frente a la lentitud de los procesos formales y la fragmentación de las políticas públicas que no logran abordar el problema de fondo del acceso al suelo.\n\n**Innovación en Planificación Sostenible y los Desafíos Climáticos**\n\nLa agenda ambiental ha escalado en importancia, y esto se refleja en el urbanismo. Cada vez más, se habla de incorporar criterios de sostenibilidad y adaptación al cambio climático en la planificación urbana. Algunas ciudades están explorando ideas como las \"ciudades de proximidad\" o \"ciudades de 15 minutos\", donde los servicios esenciales están al alcance en distancias cortas, reduciendo la necesidad de transporte motorizado. Esto implica promover barrios con usos mixtos (viviendas, comercios, oficinas) y potenciar el transporte público y las ciclovías. También hay proyectos que buscan proteger humedales urbanos, crear corredores verdes y fomentar la infraestructura que ayude a mitigar las inundaciones o las \"islas de calor\" en las ciudades.\n\nEstas iniciativas suelen ser impulsadas por equipos técnicos dentro de los gobiernos locales, con el apoyo de universidades, centros de investigación y organizaciones ambientales. A menudo, reciben financiamiento y asesoramiento de agencias de cooperación internacional. Si bien estos proyectos piloto muestran resultados prometedores en términos de calidad ambiental y mejora del espacio público en áreas específicas, su principal desafío es la escala. La mayoría son iniciativas aisladas que luchan por integrarse en políticas urbanas más amplias y duraderas. Funciona bien la conciencia creciente sobre la importancia de lo ambiental, pero los problemas surgen por la falta de recursos económicos consistentes y la dificultad para que estas ideas se conviertan en normativas obligatorias que trasciendan los cambios de gobierno. La tensión reside entre el discurso de la sostenibilidad y la realidad de las decisiones de inversión y desarrollo, donde a menudo prevalecen criterios de rentabilidad a corto plazo sobre los beneficios ambientales y sociales a largo plazo.\n\n**3. Indicadores clave a monitorear**\n\n1.  **Tasa de Expansión Urbana neta vs. Crecimiento Poblacional:** Este indicador nos dice cuánto crece la mancha urbana (la superficie construida de una ciudad) en comparación con el aumento de su población. Si la expansión de la superficie urbana supera con creces el crecimiento de habitantes, sugiere un desarrollo territorial ineficiente, con posibles consecuencias como mayores costos de infraestructura y servicios, y pérdida de suelo productivo o espacios verdes.\n2.  **Porcentaje de Población en Asentamientos Informales con Acceso Pleno a Servicios Básicos:** Refleja la efectividad de las políticas de integración sociourbana y de acceso a la vivienda digna. Un aumento de este porcentaje indicaría mejoras concretas en las condiciones de vida de las poblaciones más vulnerables, mientras que un estancamiento o retroceso señalaría una persistencia o agudización del déficit habitacional y la informalidad.\n3.  **Cantidad de Municipios con Planes de Ordenamiento Territorial Actualizados y Validado:** Muestra cuántos gobiernos locales tienen herramientas activas y modernas para planificar su desarrollo. Un número creciente indica un mayor compromiso con una gestión territorial ordenada y predecible, mientras que un bajo número sugiere planificación fragmentada, arbitrariedad en las decisiones sobre el uso del suelo y una mayor vulnerabilidad al crecimiento desordenado.\n4.  **Inversión Pública en Infraestructura Urbana y Espacios Verdes por Habitante en Áreas Periurbanas:** Este indicador mide cuánto dinero se destina a mejorar la calidad de vida en las zonas de expansión de las ciudades. Un aumento sostenido reflejaría una preocupación por integrar adecuadamente estas áreas, dotándolas de los servicios necesarios y evitando la formación de nuevos \"bolsones\" de informalidad y precariedad, además de promover la sostenibilidad.\n5.  **Precio Promedio del Metro Cuadrado de Suelo Urbano con Servicios en Ciudades Principales (en relación con el Salario Mínimo Vital y Móvil):** Monitorear la evolución de los precios del suelo y su accesibilidad es crucial. Si el costo del metro cuadrado crece mucho más rápido que el poder adquisitivo de los salarios, evidencia una creciente dificultad para el acceso formal a la tierra y la vivienda, impulsando la especulación inmobiliaria y aumentando la presión sobre la informalidad."
  }
}