{
  "pais": "Argentina",
  "categoria": "Infraestructura y transporte",
  "subcategoria": "Infraestructura vial y ferroviaria",
  "analisis": {
    "2026-02": "**1. Situación anterior**\n\nEn la última década, la infraestructura vial y ferroviaria de Argentina ha transitado un camino con avances y retrocesos, marcado por la inestabilidad económica y cambios en las prioridades de gobierno. Hacia mediados de los 2010, hubo un intento por modernizar y expandir la red vial, con la visión de transformar rutas nacionales en autopistas y autovías. Varios proyectos importantes se iniciaron, muchos de ellos bajo la modalidad de obra pública tradicional, buscando mejorar la conectividad entre centros productivos y puertos. Sin embargo, a partir de 2018-2019, la severa crisis económica golpeó con fuerza, provocando la paralización o drástica desaceleración de muchas de esas obras por falta de financiamiento, dejando tramos sin terminar o en estado precario. La incursión en modelos de Participación Público-Privada (PPP) para grandes corredores viales también se vio frustrada por la incertidumbre macroeconómica y dificultades para cerrar el financiamiento, dejando expectativas sin cumplir y contratos en revisión.\n\nEn el ámbito ferroviario, la historia fue similar. Durante este período, se hizo un esfuerzo importante por reactivar y modernizar el sistema de cargas, particularmente en líneas estratégicas como el Belgrano Cargas, con inversiones significativas, a menudo respaldadas por créditos internacionales. El objetivo era reducir costos logísticos para las economías regionales. En las áreas urbanas, especialmente en el Gran Buenos Aires, se continuó con la renovación de vías, electrificación y adquisición de nuevo material rodante para los trenes de pasajeros. No obstante, estas mejoras fueron localizadas y no lograron revertir el deterioro generalizado de una red que arrastraba décadas de desinversión. Las conexiones de larga distancia para pasajeros, por ejemplo, siguieron siendo marginales o directamente inexistentes en la mayoría del país, reflejando una falta de visión integral y sostenida para el desarrollo de un sistema ferroviario que pudiera complementar eficientemente la red vial. En resumen, fue una etapa de avances a trompicones, donde la voluntad política y los planes de inversión chocaron repetidamente con las limitaciones económicas y la falta de continuidad.\n\n**2. Situación actual**\n\nAl iniciar febrero de 2026, el panorama de la infraestructura vial y ferroviaria en Argentina se caracteriza por una marcada contracción de la inversión pública y un intento de reconfigurar el rol del Estado, empujando con fuerza hacia una mayor participación del sector privado.\n\n**La Parálisis y la Reevaluación de Proyectos**\nDesde finales de 2023 y a lo largo de 2024, el gobierno nacional implementó una política de fuerte ajuste fiscal, que derivó en la drástica reducción y, en muchos casos, la paralización total de obras públicas en todo el país. Esta medida ha afectado directamente a una vasta cantidad de proyectos viales y ferroviarios que estaban en curso, desde la construcción de nuevas rutas y puentes hasta la renovación de vías férreas y pasos a nivel.\nLas acciones concretas han incluido recortes presupuestarios masivos a organismos como Vialidad Nacional y a las empresas ferroviarias públicas. La consigna es clara: el Estado nacional reducirá al mínimo su rol como ejecutor directo de obras. Quienes llevan a cabo esta política son principalmente el Ministerio de Economía y el Ministerio de Infraestructura, con un claro objetivo de equilibrio fiscal. Esto ha generado una enorme presión sobre las provincias, a quienes se les sugiere asumir la financiación y ejecución de obras que antes dependían del Tesoro nacional, aunque muchas carecen de los recursos para hacerlo.\nLas consecuencias más evidentes y negativas son la proliferación de obras inconclusas: rutas con desvíos permanentes, puentes a medio construir que no habilitan el paso y tramos ferroviarios con vías tendidas pero sin operatividad. Esto genera un efecto cascada: aumento del desempleo en el sector de la construcción, mayores costos logísticos para el transporte de mercaderías (especialmente para el sector agropecuario, que depende crucialmente de rutas en buen estado), y riesgos crecientes para la seguridad vial. La confianza de los contratistas en el Estado también se ha visto erosionada, ya que muchos reclaman pagos por trabajos ya realizados. El \"problema\" aquí es que la drástica reducción de la inversión pública, aunque logra un ahorro fiscal inmediato, tiene un costo social y económico diferido pero significativo en términos de competitividad y calidad de vida.\n\n**El Intento de Reanimar la Participación Privada y el Modelo de Concesiones**\nFrente a la retirada del Estado como inversor principal, el gobierno está apostando fuertemente a reactivar la inversión privada en infraestructura. La medida central es la revisión y simplificación de los marcos legales para las concesiones y los nuevos esquemas de Participación Público-Privada (PPP). El objetivo es ofrecer un entorno más predecible y atractivo para inversores, tanto nacionales como extranjeros, que estén dispuestos a financiar, construir, operar y mantener la infraestructura a cambio de un peaje o un canon.\nEl Ministerio de Infraestructura y la Secretaría de Finanzas son los principales impulsores de estos cambios, trabajando en rediseñar los pliegos de licitación y los modelos contractuales para proyectos viales y ferroviarios. Se busca aprender de los errores del pasado, intentando generar contratos más robustos y mecanismos de resolución de controversias más eficientes.\nLos resultados hasta la fecha son mixtos y, en gran medida, incipientes. Si bien hay interés manifestado por algunas empresas y fondos de inversión, la concreción de nuevos proyectos de gran envergadura bajo estas modalidades es aún limitada. La principal tensión radica en la brecha entre el deseo del gobierno de atraer capital y la realidad económica del país. Los inversores privados requieren estabilidad macroeconómica, previsibilidad regulatoria, ausencia de cepos cambiarios y tasas de retorno que justifiquen el riesgo. Con una inflación aún elevada y la persistencia de cierta incertidumbre económica, financiar proyectos de infraestructura a largo plazo en Argentina sigue siendo percibido como de alto riesgo, lo que encarece el capital y reduce la cantidad de interesados. Funciona la intención de cambiar el paradigma, pero el problema es que las condiciones macroeconómicas actuales no son las ideales para materializar esta visión, lo que lleva a un cuello de botella entre la voluntad política y la capacidad de ejecución real.\n\n**El Estado de la Red Existente y la Priorización de Mantenimiento**\nCon la virtual paralización de nuevas obras, la atención se ha volcado, por necesidad, al mantenimiento básico de la infraestructura existente. Sin embargo, incluso esta área crítica enfrenta serias limitaciones presupuestarias. La administración actual se ve obligada a priorizar qué tramos viales y ferroviarios reciben atención, enfocándose en aquellos considerados esenciales para la conectividad productiva o con mayores riesgos de seguridad.\nVialidad Nacional, con un presupuesto reducido, se concentra en bacheo de emergencia y reparaciones puntuales en corredores estratégicos para el transporte de granos y otras exportaciones. En el ámbito ferroviario, las empresas que gestionan la infraestructura hacen malabares para mantener la operatividad, lo que a menudo implica reducir la velocidad de los trenes en tramos deteriorados para evitar descarrilamientos.\nLas consecuencias son palpables: la calidad general de las rutas nacionales y provinciales continúa en declive, lo que se traduce en mayor desgaste de vehículos, mayores tiempos de viaje, más accidentes y un aumento significativo en los costos de flete para toda la cadena productiva. La lentitud y falta de confiabilidad del sistema ferroviario, en los tramos donde aún funciona, limita su capacidad para competir con el transporte automotor, incluso para cargas pesadas a larga distancia. El problema es que el mantenimiento es una inversión continua y no una solución de emergencia; décadas de subinversión no se revierten con parches. La tensión se da entre la necesidad imperiosa de mantener una red vital para la economía y la capacidad fiscal extremadamente limitada para hacerlo de manera efectiva, lo que condena a la infraestructura a un proceso de deterioro gradual que impactará fuertemente en la competitividad del país a mediano plazo.\n\n**3. Indicadores clave a monitorear**\n\n1.  **Inversión Real en Infraestructura Vial y Ferroviaria (nacional y provincial, en porcentaje del PIB):** Este indicador muestra el esfuerzo total que el país, a través de sus diferentes niveles de gobierno, destina a mantener y expandir su infraestructura. Es crucial para entender si el volumen de inversión es suficiente para cubrir el deterioro anual y permitir un crecimiento. Un porcentaje bajo y decreciente indica un futuro de infraestructura deficiente.\n2.  **Estado de la Red Vial Nacional (porcentaje de rutas en estado \"malo\" o \"regular\"):** Proporciona una medida directa de la calidad de las carreteras. Un aumento en el porcentaje de rutas en condiciones deficientes es un signo de falta de mantenimiento adecuado y de inversión en mejoras, lo que impacta directamente en costos logísticos, seguridad vial y tiempos de viaje.\n3.  **Volumen de Carga Transportada por Ferrocarril (toneladas-kilómetro):** Este indicador mide la capacidad y eficiencia del sistema ferroviario para mover la producción. Un estancamiento o disminución, a pesar de que la producción nacional crezca, podría señalar problemas en la infraestructura ferroviaria (como vías en mal estado que exigen reducir la velocidad) o una falta de inversión que lo hace menos competitivo frente al transporte automotor.\n4.  **Concreción de Proyectos de Infraestructura Privados (monto de inversión comprometido y número de proyectos iniciados):** Permite evaluar si la estrategia de atraer capital privado está teniendo éxito. Un aumento sostenido indicaría que las condiciones macroeconómicas y los marcos regulatorios son percibidos como favorables por los inversores. Si se mantiene bajo, refleja una persistencia de desconfianza o de barreras para la inversión.\n5.  **Costos Logísticos de Transporte (porcentaje sobre el valor final del producto):** Aunque no es exclusivo de la infraestructura, este indicador refleja la eficiencia general del sistema de transporte de un país. Si los costos logísticos, en particular los asociados al transporte terrestre y ferroviario, son altos y no se reducen, puede ser un síntoma de infraestructura deficiente, lo que resta competitividad a las exportaciones y encarece los productos a nivel local."
  }
}